ds5ctl/__init__.py
ds5ctl/__main__.py
ds5ctl/gui.py
ds5ctl/hid.py
ds5ctl-0.2.1.dist-info/entry_points.txt
ds5ctl-0.2.1.dist-info/WHEEL
ds5ctl-0.2.1.dist-info/METADATA
ds5ctl-0.2.1.dist-info/RECORD
