Metadata-Version: 2.1
Name: ds5ctl
Version: 0.2.1
Summary: Some reference implementations of DS5-related I/O
Home-page: https://github.com/theY4Kman/ds5ctl
License: MIT
Author: Zach Kanzler
Author-email: they4kman@gmail.com
Requires-Python: >=3.10,<4.0
Classifier: License :: OSI Approved :: MIT License
Classifier: Programming Language :: Python :: 3
Classifier: Programming Language :: Python :: 3.10
Requires-Dist: dearpygui (>=1.6.2,<2.0.0)
Requires-Dist: hidapi (>=0.11.2,<0.12.0)
Requires-Dist: mopyx (>=1.1.1,<2.0.0)
Requires-Dist: pytest (>=7.0,<8.0)
Project-URL: Repository, https://github.com/theY4Kman/ds5ctl
